{
    "username": "jeslinpjames",
    "name": "Jeslin P James",
    "bio": "",
    "location": null,
    "avatar_url": "https://avatars.githubusercontent.com/u/114094231?u=10a7e1147cf1f3f124ccfcba09223d07400af14a&v=4",
    "profile_url": "https://github.com/jeslinpjames",
    "top_languages": [
        [
            "C++",
            7
        ],
        [
            "Python",
            12
        ],
        [
            "R",
            1
        ]
    ],
    "top_projects": [
        {
            "name": "HackForTomorrow",
            "description": null,
            "score": 3.251322808478021,
            "stars": 0,
            "forks": 4,
            "language": "JavaScript",
            "url": "https://github.com/jeslinpjames/HackForTomorrow",
            "updatedAt": "2024-12-25T12:21:49Z"
        },
        {
            "name": "AISamasya",
            "description": null,
            "score": 2.598405926071626,
            "stars": 0,
            "forks": 3,
            "language": "JavaScript",
            "url": "https://github.com/jeslinpjames/AISamasya",
            "updatedAt": "2024-12-10T04:34:36Z"
        },
        {
            "name": "ViT-Video-Feature-Extraction",
            "description": null,
            "score": 1.6325468140468729,
            "stars": 1,
            "forks": 0,
            "language": "Python",
            "url": "https://github.com/jeslinpjames/ViT-Video-Feature-Extraction",
            "updatedAt": "2024-03-02T03:58:29Z"
        },
        {
            "name": "Design_and_Algorithm_Analysis",
            "description": null,
            "score": 1.5491638729965285,
            "stars": 1,
            "forks": 0,
            "language": "C++",
            "url": "https://github.com/jeslinpjames/Design_and_Algorithm_Analysis",
            "updatedAt": "2023-12-21T06:14:11Z"
        },
        {
            "name": "StudySphere",
            "description": null,
            "score": 1.299341792681421,
            "stars": 0,
            "forks": 1,
            "language": "JavaScript",
            "url": "https://github.com/jeslinpjames/StudySphere",
            "updatedAt": "2024-04-17T05:18:18Z"
        },
        {
            "name": "Java_Project",
            "description": null,
            "score": 1.2009451599996233,
            "stars": 0,
            "forks": 1,
            "language": "Java",
            "url": "https://github.com/jeslinpjames/Java_Project",
            "updatedAt": "2023-08-21T05:33:14Z"
        },
        {
            "name": "cpp_lab",
            "description": null,
            "score": 1.1921687367334404,
            "stars": 0,
            "forks": 1,
            "language": "C++",
            "url": "https://github.com/jeslinpjames/cpp_lab",
            "updatedAt": "2023-02-11T13:58:15Z"
        },
        {
            "name": "CV_ScoringSystem",
            "description": null,
            "score": 0.5848068678769202,
            "stars": 0,
            "forks": 0,
            "language": "Python",
            "url": "https://github.com/jeslinpjames/CV_ScoringSystem",
            "updatedAt": "2024-12-14T07:09:09Z"
        }
    ],
    "followers": 25,
    "following": 34,
    "public_repos": 48,
    "pull_requests_merged": 19,
    "issues_closed": 0,
    "achievements": {
        "total_contributions": 517,
        "repositories_contributed_to": 9
    },
    "social_accounts": [
        {
            "provider": "linkedin",
            "url": "https://www.linkedin.com/in/jeslin-p-james-059463256/"
        }
    ],
    "activity_summary": {
        "jeslinpjames/AISamasya": {
            "link": "https://github.com/jeslinpjames/AISamasya",
            "summary": "Recent activities in the AISamasya repository include multiple push events with updates such as adding a nod detection feature, commenting on code lines, updating requirements, containerization completion, and backend code additions. These changes indicate significant development progress in the project, with a focus on enhancing its functionalities and robustness."
        },
        "jeslinpjames/R4DS": {
            "link": "https://github.com/jeslinpjames/R4DS",
            "summary": "The R4DS repository has seen a series of push events, primarily focusing on adding questions from cycle 3, including Q2 to Q6, indicating a steady effort in expanding the project's content or dataset, possibly for educational or research purposes."
        },
        "jeslinpjames/BigDataAnalytics": {
            "link": "https://github.com/jeslinpjames/BigDataAnalytics",
            "summary": "Although less recent, activities in the BigDataAnalytics repository are noteworthy, with push events involving the installation of Spark and Scala, data preprocessing, and cleaning of the Titanic dataset, alongside sort and aggregate table operations. These activities suggest a focus on setting up a big data analytics environment and performing preliminary data analysis tasks."
        },
        "LejitAI/lejit-backend-node": {
            "link": "https://github.com/LejitAI/lejit-backend-node",
            "summary": "The lejit-backend-node repository has a recent pull request event related to a login feature, indicating ongoing development, possibly aimed at enhancing user authentication or authorization aspects of the backend system."
        }
    },
    "profile_summary": "Jeslin P James is a highly skilled developer with expertise in programming languages such as C++, Python, and R. With a strong background in software development, Jeslin has established himself as a reliable and innovative professional in the field. His technical skills are complemented by a growing professional network, with 25 followers who appreciate his contributions to the developer community. Jeslin's active development work is evident in his 48 public repositories, showcasing his ability to design, develop, and deploy high-quality software solutions.\n\nAs a seasoned developer, Jeslin brings a unique value proposition to the table, combining technical expertise with a passion for innovation and collaboration. With a strong foundation in computer science and software engineering, Jeslin is well-versed in industry-relevant keywords such as data analysis, machine learning, and algorithms. His expertise in C++, Python, and R enables him to tackle complex software development projects with ease, making him a valuable asset to any organization. With a strong online presence and a commitment to delivering high-quality work, Jeslin is poised to make a significant impact in the world of software development."
}