{
    "username": "jreyes289",
    "name": "Juan Reyes",
    "bio": "",
    "location": "Bogota",
    "avatar_url": "https://avatars.githubusercontent.com/u/25044001?u=670bbf185734fd9f6b40e2b5c19676040946e453&v=4",
    "profile_url": "https://github.com/JReyes289",
    "top_languages": [
        [
            "Jupyter Notebook",
            1
        ]
    ],
    "top_projects": [
        {
            "name": "HCI-CS6750",
            "description": null,
            "score": 0.1680490789293225,
            "stars": 0,
            "forks": 0,
            "language": null,
            "url": "https://github.com/JReyes289/HCI-CS6750",
            "updatedAt": "2024-01-13T18:44:51Z",
            "isPinned": false,
            "homepage": null
        },
        {
            "name": "extendedcase4",
            "description": null,
            "score": 0.06617799122401312,
            "stars": 0,
            "forks": 0,
            "language": "Jupyter Notebook",
            "url": "https://github.com/JReyes289/extendedcase4",
            "updatedAt": "2019-11-08T21:23:05Z",
            "isPinned": false,
            "homepage": null
        }
    ],
    "followers": 7,
    "following": 20,
    "public_repos": 32,
    "pull_requests_merged": 0,
    "issues_closed": 0,
    "achievements": {
        "total_contributions": 693,
        "repositories_contributed_to": 0
    },
    "social_accounts": [],
    "readme_content": "",
    "profile_summary": "I'm Juan Reyes, a skilled data scientist with expertise in harnessing the power of Jupyter Notebook to drive business value and innovation. I stay ahead of the curve by actively contributing to 32 public repositories, where I share knowledge and collaborate with a community of 7 followers. My passion for data-driven insights has led me to develop scalable solutions, empowering organizations to make informed decisions with precision and speed. With a strong foundation in Jupyter Notebook, I craft intuitive, high-performance tools that equip teams to tackle complex problems with confidence."
}