{
    "username": "kanishk6030",
    "name": "Kanishka Vats",
    "bio": "I am Undergraduate Student at Cochin University College Of Engineering Kuttanad\r\npursuing my Btech degree in Information Technology\r\n",
    "location": "Bihar India",
    "avatar_url": "https://avatars.githubusercontent.com/u/169339223?v=4",
    "profile_url": "https://github.com/kanishk6030",
    "top_languages": [
        [
            "C++",
            1
        ],
        [
            "CSS",
            7
        ]
    ],
    "top_projects": [
        {
            "name": "virtual-id-card-generator",
            "description": null,
            "score": 0.38959545325840733,
            "stars": 0,
            "forks": 0,
            "language": "CSS",
            "url": "https://github.com/kanishk6030/virtual-id-card-generator",
            "updatedAt": "2024-11-02T16:32:15Z"
        },
        {
            "name": "Weather-App",
            "description": null,
            "score": 0.36344830578702164,
            "stars": 0,
            "forks": 0,
            "language": "CSS",
            "url": "https://github.com/kanishk6030/Weather-App",
            "updatedAt": "2024-10-19T16:37:50Z"
        },
        {
            "name": "Color-Picker",
            "description": null,
            "score": 0.3325308619860464,
            "stars": 0,
            "forks": 0,
            "language": "CSS",
            "url": "https://github.com/kanishk6030/Color-Picker",
            "updatedAt": "2024-09-20T12:22:35Z"
        },
        {
            "name": "QR-generator",
            "description": null,
            "score": 0.3317271416919969,
            "stars": 0,
            "forks": 0,
            "language": "CSS",
            "url": "https://github.com/kanishk6030/QR-generator",
            "updatedAt": "2024-09-19T07:07:04Z"
        },
        {
            "name": "To-do-list",
            "description": null,
            "score": 0.3293896685627789,
            "stars": 0,
            "forks": 0,
            "language": "CSS",
            "url": "https://github.com/kanishk6030/To-do-list",
            "updatedAt": "2024-09-16T09:56:59Z"
        },
        {
            "name": "Counter",
            "description": null,
            "score": 0.3278895665865049,
            "stars": 0,
            "forks": 0,
            "language": "CSS",
            "url": "https://github.com/kanishk6030/Counter",
            "updatedAt": "2024-09-14T06:01:26Z"
        },
        {
            "name": "Tic-Tac-Toe",
            "description": null,
            "score": 0.3236435191376674,
            "stars": 0,
            "forks": 0,
            "language": "CSS",
            "url": "https://github.com/kanishk6030/Tic-Tac-Toe",
            "updatedAt": "2024-09-09T15:07:16Z"
        },
        {
            "name": "SKYBUG",
            "description": null,
            "score": 0.27810596618122624,
            "stars": 0,
            "forks": 0,
            "language": "C++",
            "url": "https://github.com/kanishk6030/SKYBUG",
            "updatedAt": "2024-05-22T11:17:21Z"
        }
    ],
    "followers": 0,
    "following": 0,
    "public_repos": 8,
    "pull_requests_merged": 0,
    "issues_closed": 0,
    "achievements": {
        "total_contributions": 32,
        "repositories_contributed_to": 0
    },
    "social_accounts": [
        {
            "provider": "linkedin",
            "url": "https://www.linkedin.com/in/kanishk-vats-27291a2b1"
        }
    ],
    "activity_summary": {
        "kanishk6030/Weather-App": {
            "link": "https://github.com/kanishk6030/Weather-App",
            "summary": "Recent activity in Weather-App repository involved several push events with iterative changes between October 19th, including commits to update icons and modify the codebase for enhanced functionality and user experience."
        },
        "kanishk6030/virtual-id-card-generator": {
            "link": "https://github.com/kanishk6030/virtual-id-card-generator",
            "summary": "Activity in virtual-id-card-generator repository included two recent push events on November 2nd, marking the second and third commits to the project with further improvements or additions to its functionality."
        }
    },
    "profile_summary": "Kanishka Vats is an up-and-coming developer specializing in innovative solutions with C++ and CSS expertise. With a keen focus on advancing his skills in the field of Information Technology, he is currently pursuing a B.tech degree at Cochin University College of Engineering Kuttanad. As an active developer, Kanishka participates in various projects, hosting eight public repositories that showcase his coding skills and creativity.\n\nWith a passion for leveraging technology to drive results, Kanishka brings a unique blend of technical proficiency and enthusiasm to the development community. As his professional network expands, he is well-positioned to forge meaningful connections and drive forward-thinking solutions within the field. Grounded in his academic pursuits and driven by a love for coding, Kanishka is dedicated to delivering exceptional results and establishing himself as a reliable and innovative developer."
}