{
    "username": "kevinthomask",
    "name": "Kevin Thomas",
    "bio": "",
    "location": null,
    "avatar_url": "https://avatars.githubusercontent.com/u/133488083?u=97ca1e3485982375aa44484a6d410ecd91d40dc8&v=4",
    "profile_url": "https://github.com/KevinThomasK",
    "top_languages": [
        [
            "TypeScript",
            3
        ],
        [
            "JavaScript",
            8
        ],
        [
            "Python",
            4
        ]
    ],
    "top_projects": [
        {
            "name": "domain-rank-client",
            "description": null,
            "score": 0.41236136661374034,
            "stars": 0,
            "forks": 0,
            "language": "JavaScript",
            "url": "https://github.com/KevinThomasK/domain-rank-client",
            "updatedAt": "2024-12-05T06:30:17Z"
        },
        {
            "name": "nirmala-germany",
            "description": null,
            "score": 0.3694178187217416,
            "stars": 0,
            "forks": 0,
            "language": "CSS",
            "url": "https://github.com/KevinThomasK/nirmala-germany",
            "updatedAt": "2024-10-28T09:01:42Z"
        },
        {
            "name": "desai-new",
            "description": null,
            "score": 0.3678690927147456,
            "stars": 0,
            "forks": 0,
            "language": "CSS",
            "url": "https://github.com/KevinThomasK/desai-new",
            "updatedAt": "2024-10-25T04:52:59Z"
        },
        {
            "name": "DesaiHomes-LP",
            "description": null,
            "score": 0.3620447074639126,
            "stars": 0,
            "forks": 0,
            "language": "CSS",
            "url": "https://github.com/KevinThomasK/DesaiHomes-LP",
            "updatedAt": "2024-10-22T05:00:06Z"
        },
        {
            "name": "AFD-LP",
            "description": null,
            "score": 0.35674427021903676,
            "stars": 0,
            "forks": 0,
            "language": "CSS",
            "url": "https://github.com/KevinThomasK/AFD-LP",
            "updatedAt": "2024-10-18T10:03:19Z"
        },
        {
            "name": "NirmalaLandingPage",
            "description": null,
            "score": 0.35074049697971493,
            "stars": 0,
            "forks": 0,
            "language": "CSS",
            "url": "https://github.com/KevinThomasK/NirmalaLandingPage",
            "updatedAt": "2024-10-14T05:48:20Z"
        },
        {
            "name": "home-away",
            "description": null,
            "score": 0.30098683821995026,
            "stars": 0,
            "forks": 0,
            "language": "TypeScript",
            "url": "https://github.com/KevinThomasK/home-away",
            "updatedAt": "2024-07-28T19:10:36Z"
        },
        {
            "name": "spiderworks-nextjs-task",
            "description": null,
            "score": 0.2924034339384601,
            "stars": 0,
            "forks": 0,
            "language": "JavaScript",
            "url": "https://github.com/KevinThomasK/spiderworks-nextjs-task",
            "updatedAt": "2024-07-05T10:40:28Z"
        }
    ],
    "followers": 0,
    "following": 3,
    "public_repos": 30,
    "pull_requests_merged": 0,
    "issues_closed": 0,
    "achievements": {
        "total_contributions": 189,
        "repositories_contributed_to": 0
    },
    "social_accounts": [
        {
            "provider": "linkedin",
            "url": "https://www.linkedin.com/in/kevin-thomas-140b231ab/"
        }
    ],
    "activity_summary": {
        "KevinThomasK/domain-rank-client": {
            "link": "https://github.com/KevinThomasK/domain-rank-client",
            "summary": "Recent activities include updates to login functionality, improvements to UI, and enhancements to job status and SEO audit features. Other notable changes include updates to rank history, rank summary, and error fixes for select item prop values. Overall, significant updates were made to enhance the domain rank client's functionality and user experience."
        },
        "KevinThomasK/nirmala-germany": {
            "link": "https://github.com/KevinThomasK/nirmala-germany",
            "summary": "Recent activities have been focused on series of minor updates with improvements to the existing codebase, with no significant feature additions or changes. These updates demonstrate ongoing maintenance and refinement of the project."
        }
    },
    "profile_summary": "Highly skilled software engineer Kevin Thomas brings extensive expertise in TypeScript, JavaScript, and Python to deliver high-quality solutions. With a strong foundation in computer science and a passion for innovation, Kevin crafts robust, scalable applications that exceed client expectations. As a seasoned developer, Kevin's proficiency spans the full development lifecycle, from design to deployment.\n\nWith an impressive portfolio of 30 public repositories, Kevin demonstrates a commitment to continuous learning, collaboration, and knowledge-sharing. As a results-driven professional with a keen eye for detail, Kevin consistently delivers reliable, efficient code that drives business success. With a unique blend of technical expertise and passion for solving complex problems, Kevin Thomas is a versatile and valuable asset to any development team."
}