{
    "error": "An unexpected error occurred: User 'tursodatabase' not found or query returned no data.",
    "activity_summary": {
        "tursodatabase/limbo": {
            "link": "https://github.com/tursodatabase/limbo",
            "summary": "Recent activities in the limbo repository include a pull request event involving documentation tweaks to the core btree, specifically updating insert_into_cell() and compute_free_space() functions, which were made on 2024-12-24."
        }
    },
    "profile_summary": null
}