{
    "aakash414": {
        "created": "2024-12-27T18:27:58.042538",
        "username": "aakash414",
        "avatar_url": "https://avatars.githubusercontent.com/u/67820270?u=fd79e0542850e66ffd42b68b97cbb66067cc23bf&v=4",
        "updated": "2024-12-27T18:27:58.042546",
        "name": "Aakash P R"
    },
    "torvalds": {
        "created": "2024-12-27T18:27:59.101234",
        "username": "torvalds",
        "avatar_url": "https://avatars.githubusercontent.com/u/1024025?v=4",
        "updated": "2024-12-27T18:27:59.101241",
        "name": "Linus Torvalds"
    },
    "jkwarner990": {
        "created": "2024-12-27T18:28:01.374811",
        "username": "jkwarner990",
        "avatar_url": "https://avatars.githubusercontent.com/u/65076015?v=4",
        "updated": "2024-12-27T18:28:01.374818",
        "name": null
    },
    "ashif-ed": {
        "created": "2024-12-27T18:28:02.013777",
        "username": "ashif-ed",
        "avatar_url": "https://avatars.githubusercontent.com/u/180147635?v=4",
        "updated": "2024-12-27T18:28:02.013785",
        "name": null
    },
    "rebin03": {
        "created": "2024-12-27T18:28:02.539333",
        "username": "rebin03",
        "avatar_url": "https://avatars.githubusercontent.com/u/82110076?u=61f61b11beba0a6b6b5d9f7aab51535dbeb6f9e3&v=4",
        "updated": "2024-12-27T18:28:02.539341",
        "name": "Muhammed Rebin"
    },
    "kartikdusad15": {
        "created": "2024-12-27T18:28:03.004796",
        "username": "kartikdusad15",
        "avatar_url": "https://avatars.githubusercontent.com/u/83664929?v=4",
        "updated": "2024-12-27T18:28:03.004804",
        "name": null
    },
    "nanda-gopal-sb": {
        "created": "2024-12-27T18:28:03.732418",
        "username": "nanda-gopal-sb",
        "avatar_url": "https://avatars.githubusercontent.com/u/146068859?u=6260f7b4c9e2381e7d95a11b8a7a42cfdcb535a9&v=4",
        "updated": "2024-12-27T18:28:03.732425",
        "name": "Nandagopal SB "
    },
    "gokulskumar": {
        "created": "2024-12-27T18:28:04.634351",
        "username": "gokulskumar",
        "avatar_url": "https://avatars.githubusercontent.com/u/84574607?v=4",
        "updated": "2024-12-27T18:28:04.634359",
        "name": null
    },
    "vighneshwho": {
        "created": "2024-12-27T18:28:05.070001",
        "username": "vighneshwho",
        "avatar_url": "https://avatars.githubusercontent.com/u/37739153?u=2db2228e7eddb6f0c24e3ddf79c3d549a8c73e0c&v=4",
        "updated": "2024-12-27T18:28:05.070008",
        "name": "Vighnesh S"
    },
    "minhajputhiyara": {
        "created": "2024-12-27T18:28:05.774721",
        "username": "minhajputhiyara",
        "avatar_url": "https://avatars.githubusercontent.com/u/137104923?u=b3a49b953853b7e02871fe91b36fa4441f69ab02&v=4",
        "updated": "2024-12-27T18:28:05.774729",
        "name": "Minhaj"
    },
    "manya706": {
        "created": "2024-12-27T18:28:06.784133",
        "username": "manya706",
        "avatar_url": "https://avatars.githubusercontent.com/u/96016153?u=412008f6b48a9c05bfecfb0aff50cc9de5d5f776&v=4",
        "updated": "2024-12-27T18:28:06.784140",
        "name": "Manya Sharma"
    },
    "javaz-t": {
        "created": "2024-12-27T18:28:07.297437",
        "username": "javaz-t",
        "avatar_url": "https://avatars.githubusercontent.com/u/147338963?u=29be510b9b6a0fd1b06afa2ba436cc5874ce1a4e&v=4",
        "updated": "2024-12-27T18:28:07.297445",
        "name": "Abdul Javaz T"
    },
    "anujt65": {
        "created": "2024-12-27T18:28:07.821736",
        "username": "anujt65",
        "avatar_url": "https://avatars.githubusercontent.com/u/123918593?u=0da66c853ae76bfac0a9f69f16afd5855b36f794&v=4",
        "updated": "2024-12-27T18:28:07.821743",
        "name": "Anuj Tadkase"
    },
    "gitster": {
        "created": "2024-12-27T18:28:08.938299",
        "username": "gitster",
        "avatar_url": "https://avatars.githubusercontent.com/u/54884?u=df04369e894b22a25b4bb7bb85121ffa481047e4&v=4",
        "updated": "2024-12-27T18:28:08.938307",
        "name": "Junio C Hamano"
    },
    "abhijithb200": {
        "created": "2024-12-27T18:28:09.423761",
        "username": "abhijithb200",
        "avatar_url": "https://avatars.githubusercontent.com/u/69154038?u=93681ed18cb8088773d993ef06c70c3762404353&v=4",
        "updated": "2024-12-27T18:28:09.423769",
        "name": "ABHIJITH B"
    },
    "gokul-krishna-r": {
        "created": "2024-12-27T18:28:09.888041",
        "username": "gokul-krishna-r",
        "avatar_url": "https://avatars.githubusercontent.com/u/55547509?u=2878b43cb3eea2b228a578df8440b9ba6f3db620&v=4",
        "updated": "2024-12-27T18:28:09.888048",
        "name": "Gokul"
    },
    "maniranjan2023": {
        "created": "2024-12-27T18:28:10.499812",
        "username": "maniranjan2023",
        "avatar_url": "https://avatars.githubusercontent.com/u/137239336?u=a917258287724f61dbfc07ed61b5cea040a8dcd9&v=4",
        "updated": "2024-12-27T18:28:10.499818",
        "name": "Maniranjan"
    },
    "ashif-code-hunter": {
        "created": "2024-12-27T18:28:11.811566",
        "username": "ashif-code-hunter",
        "avatar_url": "https://avatars.githubusercontent.com/u/71429125?u=97f5ffb2b70a53b80f47915e0f730194bf95fc84&v=4",
        "updated": "2024-12-27T18:28:11.811573",
        "name": "Ashif"
    },
    "gyanaprakashsahoo7853": {
        "created": "2024-12-27T18:28:12.278081",
        "username": "gyanaprakashsahoo7853",
        "avatar_url": "https://avatars.githubusercontent.com/u/158683308?u=a2adab44751f8802d9224b435f3016e3809a8c9c&v=4",
        "updated": "2024-12-27T18:28:12.278089",
        "name": "GYANA_PRAKASH_SAHOO"
    },
    "soorya005": {
        "created": "2024-12-27T18:28:12.798267",
        "username": "soorya005",
        "avatar_url": "https://avatars.githubusercontent.com/u/165376922?u=0a60acee4c732f84ff633c4be86a3889f781f4f4&v=4",
        "updated": "2024-12-27T18:28:12.798274",
        "name": "Soorya A P"
    },
    "jagriti2425": {
        "created": "2024-12-27T18:28:13.790188",
        "username": "jagriti2425",
        "avatar_url": "https://avatars.githubusercontent.com/u/136254739?v=4",
        "updated": "2024-12-27T18:28:13.790195",
        "name": null
    },
    "akrsh47": {
        "created": "2024-12-27T18:28:14.425811",
        "username": "akrsh47",
        "avatar_url": "https://avatars.githubusercontent.com/u/173702791?u=f5dc5149bb19f6e9c7eff358020f858f3ecabad1&v=4",
        "updated": "2024-12-27T18:28:14.425818",
        "name": "Akarsh Balachandran"
    },
    "tarjmul810": {
        "created": "2024-12-27T18:28:14.837066",
        "username": "tarjmul810",
        "avatar_url": "https://avatars.githubusercontent.com/u/171965244?v=4",
        "updated": "2024-12-27T18:28:14.837072",
        "name": "Tarjmul Qasim"
    },
    "olawale-ib": {
        "created": "2024-12-27T18:28:18.345131",
        "username": "olawale-ib",
        "avatar_url": "https://avatars.githubusercontent.com/u/117480453?u=066dd3bae55114f4f1083d578b7e4131d12a6b02&v=4",
        "updated": "2024-12-27T18:28:18.345137",
        "name": "Afeez Musa"
    },
    "noel6161131110": {
        "created": "2024-12-27T18:28:24.577319",
        "username": "noel6161131110",
        "avatar_url": "https://avatars.githubusercontent.com/u/75027970?u=6a6185de592a1a05e6ed35ca66e0ffd1496b9a7c&v=4",
        "updated": "2024-12-27T18:28:24.577326",
        "name": "NOEL PAUL GEORGE"
    },
    "mrzubairdotin": {
        "created": "2024-12-27T18:28:28.337070",
        "username": "mrzubairdotin",
        "avatar_url": "https://avatars.githubusercontent.com/u/156564399?u=684ad548a2280a4951b6e1fec0f604b9b768c5ec&v=4",
        "updated": "2024-12-27T18:28:28.337077",
        "name": "Mr Zubair"
    },
    "kiranmurali93": {
        "created": "2024-12-27T18:28:28.779256",
        "username": "kiranmurali93",
        "avatar_url": "https://avatars.githubusercontent.com/u/44119868?u=c51c33231ecf9ac1e5240993819d79f6bb453fc8&v=4",
        "updated": "2024-12-27T18:28:28.779267",
        "name": "KIRAN"
    },
    "rahulporuri": {
        "created": "2024-12-27T18:28:29.208422",
        "username": "rahulporuri",
        "avatar_url": "https://avatars.githubusercontent.com/u/1926457?u=e291bf789509a32325a02acb155f5bffb93ec300&v=4",
        "updated": "2024-12-27T18:28:29.208429",
        "name": "Poruri Sai Rahul"
    },
    "sheral18": {
        "created": "2024-12-27T18:28:29.685323",
        "username": "sheral18",
        "avatar_url": "https://avatars.githubusercontent.com/u/93430457?u=01e6f055b6856d7b942763f830b384dc4a34729c&v=4",
        "updated": "2024-12-27T18:28:29.685330",
        "name": "Sheral Waskar"
    },
    "prashantug21": {
        "created": "2024-12-27T18:28:30.771791",
        "username": "prashantug21",
        "avatar_url": "https://avatars.githubusercontent.com/u/99468316?v=4",
        "updated": "2024-12-27T18:28:30.771798",
        "name": "Prashant Yadav"
    },
    "naaji-navas": {
        "created": "2024-12-27T18:28:31.375942",
        "username": "naaji-navas",
        "avatar_url": "https://avatars.githubusercontent.com/u/104789565?u=a1de3bcf7bbfd4a25b6839184104c282f6124bbf&v=4",
        "updated": "2024-12-27T18:28:31.375949",
        "name": "Najid Navas"
    },
    "progprnv": {
        "created": "2024-12-27T18:28:31.900904",
        "username": "progprnv",
        "avatar_url": "https://avatars.githubusercontent.com/u/145828371?u=4a779d1fc0f06da5a5ee30b6552bcabf42129144&v=4",
        "updated": "2024-12-27T18:28:31.900911",
        "name": "progprnv"
    },
    "mohammed-haseeb": {
        "created": "2024-12-27T18:28:32.400553",
        "username": "mohammed-haseeb",
        "avatar_url": "https://avatars.githubusercontent.com/u/108626850?u=147ffb5bb2c7140cc42a9c1f56610b5b27eb5f06&v=4",
        "updated": "2024-12-27T18:28:32.400559",
        "name": "Mohammed Haseeb"
    },
    "axiomaabsurdo": {
        "created": "2024-12-27T18:28:37.112435",
        "username": "axiomaabsurdo",
        "avatar_url": "https://avatars.githubusercontent.com/u/20176256?u=90a7c9aabb8e5cab88e910b4ab594150761f363b&v=4",
        "updated": "2024-12-27T18:28:37.112442",
        "name": "Matias Mortara"
    },
    "ananthanir": {
        "created": "2024-12-27T18:28:38.103387",
        "username": "ananthanir",
        "avatar_url": "https://avatars.githubusercontent.com/u/25743008?u=73cdc489fbe364224f2a5be81a8c81aacde9b994&v=4",
        "updated": "2024-12-27T18:28:38.103393",
        "name": "Ananthan"
    },
    "sanjkrsna": {
        "created": "2024-12-27T18:28:38.694325",
        "username": "sanjkrsna",
        "avatar_url": "https://avatars.githubusercontent.com/u/92753357?u=4f6e725a0866c85b863b6e1c3d1606af669baa30&v=4",
        "updated": "2024-12-27T18:28:38.694333",
        "name": "Sanjay Krishna"
    },
    "idhanush": {
        "created": "2024-12-27T18:28:39.240917",
        "username": "idhanush",
        "avatar_url": "https://avatars.githubusercontent.com/u/119786916?u=2626bc9ac6f0d83ec375022c30fab20099670726&v=4",
        "updated": "2024-12-27T18:28:39.240924",
        "name": "Dhanush"
    },
    "sharonkynu": {
        "created": "2024-12-27T18:28:39.675471",
        "username": "sharonkynu",
        "avatar_url": "https://avatars.githubusercontent.com/u/107600686?v=4",
        "updated": "2024-12-27T18:28:39.675478",
        "name": "SHARON SHAJI"
    },
    "sivaguruk": {
        "created": "2024-12-27T18:28:40.248249",
        "username": "sivaguruk",
        "avatar_url": "https://avatars.githubusercontent.com/u/144508506?v=4",
        "updated": "2024-12-27T18:28:40.248256",
        "name": "SIVA GURU K"
    },
    "sunithvs": {
        "created": "2024-12-27T18:28:47.854863",
        "username": "sunithvs",
        "avatar_url": "https://avatars.githubusercontent.com/u/63339782?u=675f431caf6eb8fbbb9cbeac62f2f17d20a3948f&v=4",
        "updated": "2024-12-27T18:28:47.854871",
        "name": "sunith vs"
    },
    "muhammedmidlajtv": {
        "created": "2024-12-27T18:28:48.290397",
        "username": "muhammedmidlajtv",
        "avatar_url": "https://avatars.githubusercontent.com/u/104316889?u=27f95f5106effd7bfbb59f7a239f76b988e2b116&v=4",
        "updated": "2024-12-27T18:28:48.290404",
        "name": "Muhammed Midlaj"
    },
    "programmerraja": {
        "created": "2024-12-27T18:28:48.752836",
        "username": "programmerraja",
        "avatar_url": "https://avatars.githubusercontent.com/u/44333589?u=337169ea048e19f3d6ddb0dec5a4deec09d2f50c&v=4",
        "updated": "2024-12-27T18:28:48.752844",
        "name": "K.Boopathi"
    },
    "revanth1718": {
        "created": "2024-12-27T18:28:49.263040",
        "username": "revanth1718",
        "avatar_url": "https://avatars.githubusercontent.com/u/109272714?u=d3e2f250d938b01904a741e3f184c7e1ca26693a&v=4",
        "updated": "2024-12-27T18:28:49.263047",
        "name": "Revanth"
    },
    "priyansh6570": {
        "created": "2024-12-27T18:28:56.344888",
        "username": "priyansh6570",
        "avatar_url": "https://avatars.githubusercontent.com/u/92854250?u=22c2f64a0bef8267c30f91ab701765adf699d7fd&v=4",
        "updated": "2024-12-27T18:28:56.344896",
        "name": "Priyansh Mishra"
    },
    "karthikgouda15": {
        "created": "2024-12-27T18:28:56.840163",
        "username": "karthikgouda15",
        "avatar_url": "https://avatars.githubusercontent.com/u/177159010?u=a27b381458db0cdf1e286f05e1961d746254eb7f&v=4",
        "updated": "2024-12-27T18:28:56.840170",
        "name": "Karthik G"
    },
    "xzxg001": {
        "created": "2024-12-27T18:28:57.292683",
        "username": "xzxg001",
        "avatar_url": "https://avatars.githubusercontent.com/u/118328452?u=8b7c7e572b9be2461d0c48a65dfe54a4d0326ba4&v=4",
        "updated": "2024-12-27T18:28:57.292690",
        "name": "xzxg001"
    },
    "gksoriginals": {
        "created": "2024-12-27T19:15:44.934278",
        "username": "gksoriginals",
        "avatar_url": "https://avatars.githubusercontent.com/u/16781355?u=703c6baa36ab397d4cc270ac1f0ecefc42be1c68&v=4",
        "updated": "2024-12-27T19:15:44.934285",
        "name": "Gopi (GKS)"
    },
    "sudosuanjal": {
        "created": "2024-12-27T19:15:48.499151",
        "username": "sudosuanjal",
        "avatar_url": "https://avatars.githubusercontent.com/u/129784615?u=e4c14e86d6d96efc57aa59a42fa02abd94d730bf&v=4",
        "updated": "2024-12-27T19:15:48.499158",
        "name": "Anjal K Biju"
    },
    "aazimanish": {
        "created": "2024-12-27T19:15:55.317568",
        "username": "aazimanish",
        "avatar_url": "https://avatars.githubusercontent.com/u/55126957?u=de42dc18429f85558f1200aa1bae7466a775640b&v=4",
        "updated": "2024-12-27T19:15:55.317575",
        "name": "Aazim Anish"
    },
    "a-nama": {
        "created": "2024-12-27T20:21:33.757905",
        "username": "a-nama",
        "avatar_url": "https://avatars.githubusercontent.com/u/145112688?u=c621a6b87e61fd602c5ed4171ac4805a13fffa40&v=4",
        "updated": "2024-12-27T20:21:33.757913",
        "name": "A_Nama"
    },
    "swalih60": {
        "created": "2024-12-27T21:18:22.187003",
        "username": "swalih60",
        "avatar_url": "https://avatars.githubusercontent.com/u/115351635?u=a2077b2d356879453b3668c19d26a7b794ac3c3b&v=4",
        "updated": "2024-12-27T21:18:22.187011",
        "name": null
    },
    "midhunnnk": {
        "created": "2024-12-27T22:19:04.330183",
        "username": "midhunnnk",
        "avatar_url": "https://avatars.githubusercontent.com/u/121388601?v=4",
        "updated": "2024-12-27T22:19:04.330191",
        "name": null
    },
    "gouthamrukmasah": {
        "created": "2024-12-27T23:19:19.242390",
        "username": "gouthamrukmasah",
        "avatar_url": "https://avatars.githubusercontent.com/u/27434140?v=4",
        "updated": "2024-12-27T23:19:19.242397",
        "name": null
    },
    "sanjeevidev": {
        "created": "2024-12-28T01:38:44.408351",
        "username": "sanjeevidev",
        "avatar_url": "https://avatars.githubusercontent.com/u/96916376?u=932e6ebb541f0be3a68f706836dfe3eda562b73f&v=4",
        "updated": "2024-12-28T01:38:44.408357",
        "name": "Sanjeevi Kumar V"
    },
    "selmanfariz18": {
        "created": "2024-12-28T01:38:54.333019",
        "username": "selmanfariz18",
        "avatar_url": "https://avatars.githubusercontent.com/u/92449535?u=c6e9e30cfdcad61b4384b67830236a6ccb79ba89&v=4",
        "updated": "2024-12-28T01:38:54.333024",
        "name": "Selmanul farizy K A"
    },
    "pauleenaphan": {
        "created": "2024-12-28T02:48:15.054794",
        "username": "pauleenaphan",
        "avatar_url": "https://avatars.githubusercontent.com/u/77126730?u=40c40bae64634189b39f8bb2c977f9d6e8f7c1c9&v=4",
        "updated": "2024-12-28T02:48:15.054800",
        "name": "Pauleena Phan"
    },
    "sankar": {
        "created": "2024-12-28T03:23:34.111156",
        "username": "sankar",
        "avatar_url": "https://avatars.githubusercontent.com/u/386432?v=4",
        "updated": "2024-12-28T03:23:34.111164",
        "name": null
    },
    "alchemist501": {
        "created": "2024-12-28T03:23:34.522058",
        "username": "alchemist501",
        "avatar_url": "https://avatars.githubusercontent.com/u/120238075?v=4",
        "updated": "2024-12-28T03:23:34.522065",
        "name": "SIYA P P"
    },
    "cyberianzed": {
        "created": "2024-12-28T04:24:34.126520",
        "username": "cyberianzed",
        "avatar_url": "https://avatars.githubusercontent.com/u/74711019?u=c672e65689ed0ea80b8bd852ddecec6f120522b6&v=4",
        "updated": "2024-12-28T04:24:34.126528",
        "name": "Jose K James"
    },
    "sarinmsari": {
        "created": "2024-12-28T04:24:34.428972",
        "username": "sarinmsari",
        "avatar_url": "https://avatars.githubusercontent.com/u/55913487?v=4",
        "updated": "2024-12-28T04:24:34.428980",
        "name": "Sarin M"
    },
    "nithin-daniel": {
        "created": "2024-12-28T04:24:34.873538",
        "username": "nithin-daniel",
        "avatar_url": "https://avatars.githubusercontent.com/u/66398646?u=61d7e224eba5ac69fb329fd9e4bd61b90eaad5ce&v=4",
        "updated": "2024-12-28T04:24:34.873546",
        "name": "Nithin Daniel"
    },
    "abelkuruvilla": {
        "created": "2024-12-28T04:24:38.354394",
        "username": "abelkuruvilla",
        "avatar_url": "https://avatars.githubusercontent.com/u/12940253?u=6c2ddd93000645823734585b38b11089f187fce9&v=4",
        "updated": "2024-12-28T04:24:38.354402",
        "name": "Abel Kuruvilla"
    },
    "nami63": {
        "created": "2024-12-28T04:24:38.880703",
        "username": "nami63",
        "avatar_url": "https://avatars.githubusercontent.com/u/128203391?u=3889e14f90b01c3a3756b2369b70e04731e852de&v=4",
        "updated": "2024-12-28T04:24:38.880711",
        "name": "Namitha Manoj"
    },
    "sarin": {
        "created": "2024-12-28T04:24:39.214922",
        "username": "sarin",
        "avatar_url": "https://avatars.githubusercontent.com/u/6974617?v=4",
        "updated": "2024-12-28T04:24:39.214929",
        "name": null
    },
    "zodwick": {
        "created": "2024-12-28T04:24:48.015643",
        "username": "zodwick",
        "avatar_url": "https://avatars.githubusercontent.com/u/115868723?u=f6524679726102da0ad6617c19917bf20f3d0291&v=4",
        "updated": "2024-12-28T04:24:48.015651",
        "name": "Anand"
    },
    "aswinasok": {
        "created": "2024-12-28T04:24:49.885661",
        "username": "aswinasok",
        "avatar_url": "https://avatars.githubusercontent.com/u/64626875?v=4",
        "updated": "2024-12-28T04:24:49.885669",
        "name": "Aswin Asok"
    },
    "sarinm": {
        "created": "2024-12-28T04:24:50.215825",
        "username": "sarinm",
        "avatar_url": "https://avatars.githubusercontent.com/u/52010976?v=4",
        "updated": "2024-12-28T04:24:50.215833",
        "name": null
    },
    "rafitc": {
        "created": "2024-12-28T05:19:08.157127",
        "username": "rafitc",
        "avatar_url": "https://avatars.githubusercontent.com/u/15951192?u=50217390df9ac8ef9f688cdda3a717ae2f8368c2&v=4",
        "updated": "2024-12-28T05:19:08.157136",
        "name": "Rafi Rasheed T C "
    },
    "octocat": {
        "created": "2024-12-28T05:19:08.599876",
        "username": "octocat",
        "avatar_url": "https://avatars.githubusercontent.com/u/583231?u=a59fef2a493e2b67dd13754231daf220c82ba84d&v=4",
        "updated": "2024-12-28T05:19:08.599884",
        "name": "The Octocat"
    },
    "salih-13": {
        "created": "2024-12-28T05:19:09.131261",
        "username": "salih-13",
        "avatar_url": "https://avatars.githubusercontent.com/u/97404688?u=96b7ed8b2ddbfb6059def3ca34260ab4443e9f26&v=4",
        "updated": "2024-12-28T05:19:09.131269",
        "name": "Mohammad Salih V S"
    },
    "vishnurnair93": {
        "created": "2024-12-28T05:19:10.120662",
        "username": "vishnurnair93",
        "avatar_url": "https://avatars.githubusercontent.com/u/11658934?u=eca298516857102317a840bbe5048bf059acd1e9&v=4",
        "updated": "2024-12-28T05:19:10.120668",
        "name": "Vishnu R"
    },
    "vis465": {
        "created": "2024-12-28T05:19:10.575298",
        "username": "vis465",
        "avatar_url": "https://avatars.githubusercontent.com/u/109803822?u=7a4dc8ac4569cb06d197bdac3b1418ccb0ff75db&v=4",
        "updated": "2024-12-28T05:19:10.575303",
        "name": "Vishal V"
    },
    "sarin-bmc": {
        "created": "2024-12-28T05:19:10.985936",
        "username": "sarin-bmc",
        "avatar_url": "https://avatars.githubusercontent.com/u/141834337?u=5f2339f306008b1eaeb39d1d6d6621694fc892d6&v=4",
        "updated": "2024-12-28T05:19:10.985943",
        "name": "Sarin M"
    },
    "aswin110": {
        "created": "2024-12-28T05:19:11.574199",
        "username": "aswin110",
        "avatar_url": "https://avatars.githubusercontent.com/u/117816692?u=49c73cf31413d5310bee951c788234a1e0f8233b&v=4",
        "updated": "2024-12-28T05:19:11.574205",
        "name": "Aswin"
    },
    "adhi2624": {
        "created": "2024-12-28T05:19:12.989700",
        "username": "adhi2624",
        "avatar_url": "https://avatars.githubusercontent.com/u/100017167?u=73c268edc8c5973676e13edf704b39c1041be117&v=4",
        "updated": "2024-12-28T05:19:12.989705",
        "name": "Adhithiyan R"
    },
    "elementaryrock": {
        "created": "2024-12-28T06:27:53.036989",
        "username": "elementaryrock",
        "avatar_url": "https://avatars.githubusercontent.com/u/109026282?v=4",
        "updated": "2024-12-28T06:27:53.036997",
        "name": "Maanas MS"
    },
    "xenomech": {
        "created": "2024-12-28T06:27:59.501069",
        "username": "xenomech",
        "avatar_url": "https://avatars.githubusercontent.com/u/50659225?u=996ba8e7f8a74aa0c6ed0b1fa646efe8873e4678&v=4",
        "updated": "2024-12-28T06:27:59.501077",
        "name": "Gokul Suresh"
    },
    "renjithn": {
        "created": "2024-12-28T06:28:01.493484",
        "username": "renjithn",
        "avatar_url": "https://avatars.githubusercontent.com/u/3293040?u=e23b38dd53c0e24ef44dbe89976b784034955651&v=4",
        "updated": "2024-12-28T06:28:01.493491",
        "name": null
    },
    "shijazks": {
        "created": "2024-12-28T06:28:02.116661",
        "username": "shijazks",
        "avatar_url": "https://avatars.githubusercontent.com/u/70143317?u=16fcc5fecef9e1c3f67d0b2ed4933f412536342b&v=4",
        "updated": "2024-12-28T06:28:02.116669",
        "name": "Shijaz ks"
    },
    "ahmadswalih": {
        "created": "2024-12-28T06:28:02.608071",
        "username": "ahmadswalih",
        "avatar_url": "https://avatars.githubusercontent.com/u/68387480?u=00e2baafd528873dc61ac81189683108b78321e1&v=4",
        "updated": "2024-12-28T06:28:02.608079",
        "name": "Ahamad salih"
    },
    "shiyas-n": {
        "created": "2024-12-28T06:28:05.527723",
        "username": "shiyas-n",
        "avatar_url": "https://avatars.githubusercontent.com/u/114045581?u=fc6793b512c518a76da48bac11496c0581a13329&v=4",
        "updated": "2024-12-28T06:28:05.527731",
        "name": "Muhammed Shiyas N"
    },
    "ajitesh72": {
        "created": "2024-12-28T06:28:06.818052",
        "username": "ajitesh72",
        "avatar_url": "https://avatars.githubusercontent.com/u/95878363?u=d4db0467863faf1628f90f9904fd6d83b1eb3f59&v=4",
        "updated": "2024-12-28T06:28:06.818060",
        "name": "Ajitesh Dubey"
    },
    "janukrishna007": {
        "created": "2024-12-28T06:28:07.428811",
        "username": "janukrishna007",
        "avatar_url": "https://avatars.githubusercontent.com/u/127822118?u=2ebf84259714c9d308d9131e77a6a023ebc39b19&v=4",
        "updated": "2024-12-28T06:28:07.428818",
        "name": "Janukrishna A.S"
    },
    "ishamsu": {
        "created": "2024-12-28T07:18:17.198588",
        "username": "ishamsu",
        "avatar_url": "https://avatars.githubusercontent.com/u/59248733?u=75e61fe51a6916132a5096bb5a3f63de25f7c0db&v=4",
        "updated": "2024-12-28T07:18:17.198596",
        "name": "Shamsu Musthafa"
    },
    "zukardex": {
        "created": "2024-12-28T07:18:17.795287",
        "username": "zukardex",
        "avatar_url": "https://avatars.githubusercontent.com/u/27881577?u=e5372f88b4ba057ab693c2708b19b150718ff8b8&v=4",
        "updated": "2024-12-28T07:18:17.795294",
        "name": "Mohammed Suhail K M"
    },
    "vinubalagopalap": {
        "created": "2024-12-28T07:18:18.402871",
        "username": "vinubalagopalap",
        "avatar_url": "https://avatars.githubusercontent.com/u/48175345?u=d1de504c7890a926c67d5b44678fb3416af08e64&v=4",
        "updated": "2024-12-28T07:18:18.402878",
        "name": "Vinu Balagopal A P"
    },
    "jobin-s": {
        "created": "2024-12-28T07:18:19.467296",
        "username": "jobin-s",
        "avatar_url": "https://avatars.githubusercontent.com/u/63976083?u=5345f3aaae9a102c10a5c692deac3557f084a0bd&v=4",
        "updated": "2024-12-28T07:18:19.467303",
        "name": "Jobin Selvanose"
    },
    "nirmalscaria": {
        "created": "2024-12-28T07:18:21.154672",
        "username": "nirmalscaria",
        "avatar_url": "https://avatars.githubusercontent.com/u/46727865?u=011861f81e5a54ed4a7de63f7408321adce68e05&v=4",
        "updated": "2024-12-28T07:18:21.154679",
        "name": "Nirmal Scaria"
    },
    "sidharthv96": {
        "created": "2024-12-28T08:24:58.448160",
        "username": "sidharthv96",
        "avatar_url": "https://avatars.githubusercontent.com/u/10703445?u=7dfa7d56aa3aa1f98764d6ed2f9a331eac01b39a&v=4",
        "updated": "2024-12-28T08:24:58.448169",
        "name": "Sidharth Vinod"
    },
    "midhunk0": {
        "created": "2024-12-28T09:19:31.453861",
        "username": "midhunk0",
        "avatar_url": "https://avatars.githubusercontent.com/u/89003388?u=be01ea98a69e3678eba7a62c6a4fac3e096bc67d&v=4",
        "updated": "2024-12-28T09:19:31.453868",
        "name": "Midhunraj"
    },
    "amjadcp": {
        "created": "2024-12-28T09:19:32.759218",
        "username": "amjadcp",
        "avatar_url": "https://avatars.githubusercontent.com/u/84246684?u=662cc39ea5017b6e540498683aaf59573bbcba07&v=4",
        "updated": "2024-12-28T09:19:32.759226",
        "name": "Amjad C P"
    },
    "mohamedfaz": {
        "created": "2024-12-28T10:19:46.450179",
        "username": "mohamedfaz",
        "avatar_url": "https://avatars.githubusercontent.com/u/145818177?u=af3ff3ad693320ef710f1d14b2e624777757f209&v=4",
        "updated": "2024-12-28T10:19:46.450187",
        "name": "Mohamed Fazil"
    },
    "m1dlj": {
        "created": "2024-12-28T10:19:49.005663",
        "username": "m1dlj",
        "avatar_url": "https://avatars.githubusercontent.com/u/150415027?v=4",
        "updated": "2024-12-28T10:19:49.005670",
        "name": null
    },
    "akshay-k-a-dev": {
        "created": "2024-12-28T10:19:49.463199",
        "username": "akshay-k-a-dev",
        "avatar_url": "https://avatars.githubusercontent.com/u/106895549?v=4",
        "updated": "2024-12-28T10:19:49.463206",
        "name": "Akshay K.a"
    },
    "binshadcs": {
        "created": "2024-12-28T10:19:50.108801",
        "username": "binshadcs",
        "avatar_url": "https://avatars.githubusercontent.com/u/68679199?u=20263e573c27501a8c36b500676ed62687716c4f&v=4",
        "updated": "2024-12-28T10:19:50.108808",
        "name": "Binshad k"
    },
    "ibaraphy": {
        "created": "2024-12-28T10:19:51.077332",
        "username": "ibaraphy",
        "avatar_url": "https://avatars.githubusercontent.com/u/151989005?u=f380eb4a8327ac0ebc6512847b7d30b32130a24e&v=4",
        "updated": "2024-12-28T10:19:51.077340",
        "name": null
    },
    "rohittp0": {
        "created": "2024-12-28T10:19:53.637736",
        "username": "rohittp0",
        "avatar_url": "https://avatars.githubusercontent.com/u/45072928?u=aefa3cd0f599858c730de4ce32b74e622e868f60&v=4",
        "updated": "2024-12-28T10:19:53.637743",
        "name": "Rohit"
    },
    "midnightcoder04": {
        "created": "2024-12-28T10:19:55.117050",
        "username": "midnightcoder04",
        "avatar_url": "https://avatars.githubusercontent.com/u/125803010?v=4",
        "updated": "2024-12-28T10:19:55.117056",
        "name": null
    },
    "nandakiran-r": {
        "created": "2024-12-28T10:19:55.385530",
        "username": "nandakiran-r",
        "avatar_url": "https://avatars.githubusercontent.com/u/115941579?v=4",
        "updated": "2024-12-28T10:19:55.385538",
        "name": "Nandakiran R"
    },
    "rishi-k-s": {
        "created": "2024-12-28T10:19:55.721917",
        "username": "rishi-k-s",
        "avatar_url": "https://avatars.githubusercontent.com/u/56212396?u=7a1556696ff18d1529b9ffcc2959fd7654219143&v=4",
        "updated": "2024-12-28T10:19:55.721924",
        "name": "Rishi Krishna"
    },
    "nandakiran": {
        "created": "2024-12-28T10:19:58.186128",
        "username": "nandakiran",
        "avatar_url": "https://avatars.githubusercontent.com/u/29790326?v=4",
        "updated": "2024-12-28T10:19:58.186135",
        "name": null
    },
    "alwinsunil": {
        "created": "2024-12-28T10:19:58.530309",
        "username": "alwinsunil",
        "avatar_url": "https://avatars.githubusercontent.com/u/64636626?u=391c2a7dcbc6349e0a908b7bfc5be9047e4352a6&v=4",
        "updated": "2024-12-28T10:19:58.530317",
        "name": "Alwin Sunil"
    },
    "vishakh-abhayan": {
        "created": "2024-12-28T10:19:58.920821",
        "username": "vishakh-abhayan",
        "avatar_url": "https://avatars.githubusercontent.com/u/94307781?u=a88ffdea9afdd4ef9997ae6d304c7b12fea0b34d&v=4",
        "updated": "2024-12-28T10:19:58.920828",
        "name": "Vishakh Abhayan"
    },
    "divyeshvora79909": {
        "created": "2024-12-28T10:19:59.238675",
        "username": "divyeshvora79909",
        "avatar_url": "https://avatars.githubusercontent.com/u/135146135?v=4",
        "updated": "2024-12-28T10:19:59.238682",
        "name": "divy.r.vora14@gmail.com"
    },
    "marahim20": {
        "created": "2024-12-28T10:19:59.720137",
        "username": "marahim20",
        "avatar_url": "https://avatars.githubusercontent.com/u/64319443?u=b73042aa554d53543432dd26b7adbe8e438a1fc9&v=4",
        "updated": "2024-12-28T10:19:59.720144",
        "name": null
    },
    "shivaacodes": {
        "created": "2024-12-28T11:15:31.424047",
        "username": "shivaacodes",
        "avatar_url": "https://avatars.githubusercontent.com/u/139482222?u=b2345c3c4d885baff2b94b124f49c209b13241e4&v=4",
        "updated": "2024-12-28T11:15:31.424054",
        "name": "Shiva "
    },
    "pattzac": {
        "created": "2024-12-28T11:15:34.124078",
        "username": "pattzac",
        "avatar_url": "https://avatars.githubusercontent.com/u/113007904?u=78fb7da66cf14c4f3052ff2504e7c4e2dfebefdf&v=4",
        "updated": "2024-12-28T11:15:34.124086",
        "name": "Pat"
    },
    "binumathew": {
        "created": "2024-12-28T12:38:14.134335",
        "username": "binumathew",
        "avatar_url": "https://avatars.githubusercontent.com/u/876584?u=1dd851b9de5385b1c2bc09fea12124466648dd11&v=4",
        "updated": "2024-12-28T12:38:14.134342",
        "name": "Binu Mathew"
    },
    "shad-ct": {
        "created": "2024-12-28T12:38:15.519660",
        "username": "shad-ct",
        "avatar_url": "https://avatars.githubusercontent.com/u/88387228?u=b12bad205f847aa81b5d438d4bff0b91d1e8b651&v=4",
        "updated": "2024-12-28T12:38:15.519668",
        "name": "Shad CT"
    },
    "sameemul-haque": {
        "created": "2024-12-28T12:38:16.077654",
        "username": "sameemul-haque",
        "avatar_url": "https://avatars.githubusercontent.com/u/110324374?u=23a40d205b9137172cc44156151daa82f938eb61&v=4",
        "updated": "2024-12-28T12:38:16.077662",
        "name": "Sameemul Haque"
    },
    "abyssalwolf": {
        "created": "2024-12-28T12:38:21.043619",
        "username": "abyssalwolf",
        "avatar_url": "https://avatars.githubusercontent.com/u/117766338?u=8ea78b258a2817c20cbc142175a655ad2cb72fe7&v=4",
        "updated": "2024-12-28T12:38:21.043627",
        "name": "Sebin Thomas"
    },
    "zhu04303661": {
        "created": "2024-12-28T13:22:03.234104",
        "username": "zhu04303661",
        "avatar_url": "https://avatars.githubusercontent.com/u/7496736?v=4",
        "updated": "2024-12-28T13:22:03.234110",
        "name": null
    },
    "am607": {
        "created": "2024-12-28T14:17:10.471848",
        "username": "am607",
        "avatar_url": "https://avatars.githubusercontent.com/u/62100210?u=0d84059a4ec73fc08e8a24f484ace73f965ea675&v=4",
        "updated": "2024-12-28T14:17:10.471854",
        "name": "AkbarMasterpadi"
    },
    "himmu5": {
        "created": "2024-12-28T14:17:12.662638",
        "username": "himmu5",
        "avatar_url": "https://avatars.githubusercontent.com/u/90271958?u=401dc73c500322984fb78ad074cfd1dadfb279d0&v=4",
        "updated": "2024-12-28T14:17:12.662645",
        "name": "Himanshu Chauhan"
    }
}